{
  "input_sigs": ["I", "II", "III", "V", "AVR", "MCL", "PLETH", "RESP"],
  "input_sigs_validation": ["II", "PLETH"],
  "output_sigs": ["ABP", "CVP", "ICP", "PAP"],
  "icd_codes": [
    "4019", "4280", "42731", "41401", "2724", "25000", "5859", "5849",
    "51881", "2859", "4240", "4241", "78552", "99592", "2762", "5119",
    "41071", "27800", "27651", "4275", "5715", "42732", "42832", "42833",
    "79902", "27652", "431"
  ],
  "input_stride": 1,
  "pressure_window": 512,
  "windows_per_chunk": 2,
  "batch_size": 64,
  "steps_per_epoch": 128,
  "window_size": 512,
  "filter_count": 128,
  "layer_count": 10,
  "strides": [4, 2],
  "kernel_sizes": [16, 8, 4],
  "dense_units": 256,
  "dropout": 0.1,
  "mean_pressure": {
    "ABP": [127, 58],
    "CVP": [18, 5.9],
    "ICP": [12.8, 6.4],
    "PAP": [43.2, 14.6]
  },
  "batch_buffer_size": 4,
  "loss_weights": {
    "output": {"pressure": 0.6, "diagnosis": 0.3},
    "sig": {"ABP": 0.6, "CVP": 0.2, "ICP": 0.1, "PAP": 0.1},
    "metric": {"systolic": 0.6, "diastolic": 0.4}
  },
  "relative_target_radius": 0.02,
  "learning_rate": 0.0003,
  "lr_boundaries": [10, 25, 150, 300, 500, 1000],
  "lr_divisors": [9, 3, 1, 2, 4, 8, 16]
}
